setup.cfg
setup.py
peewee_base_model/__init__.py
peewee_base_model/models.py
peewee_base_model.egg-info/PKG-INFO
peewee_base_model.egg-info/SOURCES.txt
peewee_base_model.egg-info/dependency_links.txt
peewee_base_model.egg-info/not-zip-safe
peewee_base_model.egg-info/requires.txt
peewee_base_model.egg-info/top_level.txt