Metadata-Version: 1.1
Name: peewee-base-model
Version: 0.0.5
Summary: Base model for peewee
Home-page: https://github.com/GhostNA/peewee-base-model
Author: Specter NA
Author-email: naspecter@gmail.com
License: MIT
Keywords: peewee
Platform: UNKNOWN
Classifier: License :: OSI Approved :: MIT License
Classifier: Programming Language :: Python :: 3.8
Classifier: Topic :: Text Processing :: Linguistic
